[
  { "id": "Google.Chrome",                "name": "Google Chrome",            "description": "Most popular web browser." },
  { "id": "Mozilla.Firefox",              "name": "Mozilla Firefox",          "description": "Privacy-friendly open-source browser." },
  { "id": "Brave.Brave",                  "name": "Brave Browser",            "description": "Chromium-based browser with ad blocking." },
  { "id": "VideoLAN.VLC",                 "name": "VLC media player",         "description": "Plays virtually any audio/video format." },
  { "id": "7zip.7zip",                    "name": "7-Zip",                    "description": "Free, open-source file archiver." },
  { "id": "RARLab.WinRAR",                "name": "WinRAR",                   "description": "Popular archive utility (trial)." },
  { "id": "Notepad++.Notepad++",          "name": "Notepad++",                "description": "Lightweight code/text editor." },
  { "id": "Microsoft.VisualStudioCode",   "name": "Visual Studio Code",       "description": "Modern code editor by Microsoft." },
  { "id": "JetBrains.Toolbox",            "name": "JetBrains Toolbox",        "description": "Manages JetBrains IDEs." },
  { "id": "Git.Git",                      "name": "Git",                      "description": "Distributed version control system." },
  { "id": "GitHub.GitHubDesktop",         "name": "GitHub Desktop",           "description": "Friendly Git GUI from GitHub." },
  { "id": "Microsoft.PowerToys",          "name": "PowerToys",                "description": "Productivity utilities from Microsoft." },
  { "id": "Microsoft.WindowsTerminal",    "name": "Windows Terminal",         "description": "Modern terminal for Windows." },
  { "id": "Python.Python.3.12",           "name": "Python 3.12",              "description": "Python programming language." },
  { "id": "OpenJS.NodeJS",                "name": "Node.js (LTS)",            "description": "JavaScript runtime." },
  { "id": "Docker.DockerDesktop",         "name": "Docker Desktop",           "description": "Container runtime for Windows." },
  { "id": "Postman.Postman",              "name": "Postman",                  "description": "API platform / HTTP client." },
  { "id": "OpenJS.Yarn",                  "name": "Yarn",                     "description": "Fast Node.js package manager." },
  { "id": "Telegram.TelegramDesktop",     "name": "Telegram Desktop",         "description": "Telegram messenger." },
  { "id": "Discord.Discord",              "name": "Discord",                  "description": "Gaming / community chat." },
  { "id": "WhatsApp.WhatsApp",            "name": "WhatsApp Desktop",         "description": "WhatsApp messenger." },
  { "id": "Zoom.Zoom",                    "name": "Zoom",                     "description": "Video conferencing." },
  { "id": "Microsoft.Teams",              "name": "Microsoft Teams",          "description": "Teams collaboration platform." },
  { "id": "SlackTechnologies.Slack",      "name": "Slack",                    "description": "Team communication." },
  { "id": "Valve.Steam",                  "name": "Steam",                    "description": "Game distribution platform." },
  { "id": "EpicGames.EpicGamesLauncher",  "name": "Epic Games Launcher",      "description": "Epic Games store launcher." },
  { "id": "ElectronicArts.EADesktop",     "name": "EA app",                   "description": "Electronic Arts launcher." },
  { "id": "GOG.Galaxy",                   "name": "GOG Galaxy",               "description": "GOG game launcher." },
  { "id": "Ubisoft.Connect",              "name": "Ubisoft Connect",          "description": "Ubisoft launcher." },
  { "id": "OBSProject.OBSStudio",         "name": "OBS Studio",               "description": "Streaming and recording suite." },
  { "id": "Streamlabs.Streamlabs",        "name": "Streamlabs",               "description": "Streaming software." },
  { "id": "Audacity.Audacity",            "name": "Audacity",                 "description": "Audio editor." },
  { "id": "GIMP.GIMP",                    "name": "GIMP",                     "description": "Free image editor." },
  { "id": "Inkscape.Inkscape",            "name": "Inkscape",                 "description": "Vector graphics editor." },
  { "id": "Krita.Krita",                  "name": "Krita",                    "description": "Free digital painting." },
  { "id": "BlenderFoundation.Blender",    "name": "Blender",                  "description": "3D creation suite." },
  { "id": "Adobe.Acrobat.Reader.64-bit",  "name": "Adobe Acrobat Reader",     "description": "PDF reader." },
  { "id": "Foxit.FoxitReader",            "name": "Foxit Reader",             "description": "Lightweight PDF reader." },
  { "id": "Spotify.Spotify",              "name": "Spotify",                  "description": "Music streaming." },
  { "id": "AnyDeskSoftwareGmbH.AnyDesk",  "name": "AnyDesk",                  "description": "Remote desktop." },
  { "id": "TeamViewer.TeamViewer",        "name": "TeamViewer",               "description": "Remote support." },
  { "id": "Mozilla.Thunderbird",          "name": "Mozilla Thunderbird",      "description": "Free email client." },
  { "id": "Bitwarden.Bitwarden",          "name": "Bitwarden",                "description": "Password manager." },
  { "id": "KeePassXCTeam.KeePassXC",      "name": "KeePassXC",                "description": "Local password manager." },
  { "id": "ProtonTechnologies.ProtonVPN", "name": "ProtonVPN",                "description": "VPN client." },
  { "id": "Mullvad.MullvadVPN",           "name": "Mullvad VPN",              "description": "Privacy-focused VPN." },
  { "id": "qBittorrent.qBittorrent",      "name": "qBittorrent",              "description": "BitTorrent client." },
  { "id": "Transmission.Transmission",    "name": "Transmission",             "description": "Lightweight torrent client." },
  { "id": "JoplinApp.Joplin",             "name": "Joplin",                   "description": "Open-source note app." },
  { "id": "Obsidian.Obsidian",            "name": "Obsidian",                 "description": "Markdown knowledge base." },
  { "id": "Notion.Notion",                "name": "Notion",                   "description": "All-in-one workspace." },
  { "id": "Logitech.Options",             "name": "Logitech Options",         "description": "Logitech mouse/keyboard tool." },
  { "id": "Razer.RazerInstaller",         "name": "Razer Synapse",            "description": "Razer device manager." },
  { "id": "NVIDIA.GeForceExperience",     "name": "NVIDIA GeForce Experience","description": "NVIDIA drivers and overlay." },
  { "id": "AdvancedMicroDevicesInc.AMDSoftwareAdrenalinEdition", "name": "AMD Adrenalin", "description": "AMD driver suite." },
  { "id": "MSI.Afterburner",              "name": "MSI Afterburner",          "description": "GPU overclock and monitor." },
  { "id": "CPUID.CPU-Z",                  "name": "CPU-Z",                    "description": "Hardware info." },
  { "id": "CPUID.HWMonitor",              "name": "HWMonitor",                "description": "Hardware sensors." },
  { "id": "TechPowerUp.GPU-Z",            "name": "GPU-Z",                    "description": "GPU info." },
  { "id": "CrystalDewWorld.CrystalDiskInfo","name":"CrystalDiskInfo",         "description": "Disk health monitor." },
  { "id": "CrystalDewWorld.CrystalDiskMark","name":"CrystalDiskMark",         "description": "Disk benchmark." },
  { "id": "REALiX.HWiNFO",                "name": "HWiNFO",                   "description": "In-depth system info." },
  { "id": "BleachBit.BleachBit",          "name": "BleachBit",                "description": "Disk cleaner." },
  { "id": "Greenshot.Greenshot",          "name": "Greenshot",                "description": "Screenshot tool." },
  { "id": "ShareX.ShareX",                "name": "ShareX",                   "description": "Powerful screenshot/share tool." },
  { "id": "Microsoft.PowerShell",         "name": "PowerShell 7",             "description": "Cross-platform PowerShell." },
  { "id": "Microsoft.DotNet.SDK.8",       "name": ".NET 8 SDK",               "description": ".NET development kit." },
  { "id": "EclipseAdoptium.Temurin.21.JDK","name":"Eclipse Temurin 21 JDK",   "description": "OpenJDK 21 LTS." },
  { "id": "TheBrowserCompany.Arc",        "name": "Arc Browser",              "description": "New-gen browser by The Browser Company." },
  { "id": "Vivaldi.Vivaldi",              "name": "Vivaldi",                  "description": "Highly customizable browser." },
  { "id": "Zen-Team.Zen-Browser",         "name": "Zen Browser",              "description": "Beautiful Firefox-based browser." }
]
